wagtail_webstories_editor/__init__.py
wagtail_webstories_editor/action_menu.py
wagtail_webstories_editor/admin.py
wagtail_webstories_editor/api_viewsets.py
wagtail_webstories_editor/apps.py
wagtail_webstories_editor/models.py
wagtail_webstories_editor/tests.py
wagtail_webstories_editor/utils.py
wagtail_webstories_editor/views.py
wagtail_webstories_editor/wagtail_hooks.py
wagtail_webstories_editor/migrations/0001_initial.py
wagtail_webstories_editor/migrations/0002_alter_webstory_title.py
wagtail_webstories_editor/migrations/0003_alter_webstory_options.py
wagtail_webstories_editor/migrations/0004_webstory_created_at.py
wagtail_webstories_editor/migrations/0005_webstoriessetting_webstoriespublisherlogo.py
wagtail_webstories_editor/migrations/0006_webstoriespublisherlogo_default.py
wagtail_webstories_editor/migrations/0007_webstoriessetting_google_analytics_id.py
wagtail_webstories_editor/migrations/0008_webstoriessetting_auto_advance_and_more.py
wagtail_webstories_editor/migrations/0009_alter_webstoriessetting_default_page_duration.py
wagtail_webstories_editor/migrations/0010_webstoriespublisherlogo_slug.py
wagtail_webstories_editor/migrations/0011_remove_webstoriespublisherlogo_slug_webstory_slug.py
wagtail_webstories_editor/migrations/0012_alter_webstory_slug.py
wagtail_webstories_editor/migrations/__init__.py
wagtail_webstories_editor/static/wagtail_webstories_editor/js/common.js
wagtail_webstories_editor/static/wagtail_webstories_editor/js/story-editor/161.js
wagtail_webstories_editor/static/wagtail_webstories_editor/js/story-editor/209.js
wagtail_webstories_editor/static/wagtail_webstories_editor/js/story-editor/209.js.LICENSE.txt
wagtail_webstories_editor/static/wagtail_webstories_editor/js/story-editor/520.js
wagtail_webstories_editor/static/wagtail_webstories_editor/js/story-editor/839.js
wagtail_webstories_editor/static/wagtail_webstories_editor/js/story-editor/839.js.LICENSE.txt
wagtail_webstories_editor-0.3.0.dist-info/licenses/LICENSE
wagtail_webstories_editor-0.3.0.dist-info/METADATA
wagtail_webstories_editor-0.3.0.dist-info/WHEEL
wagtail_webstories_editor-0.3.0.dist-info/top_level.txt
wagtail_webstories_editor-0.3.0.dist-info/RECORD
